{
  "abilities": [
    "すいすい", 
    "いしあたま", 
    "がんじょう"
  ], 
  "egg_groups": [
    "すいちゅう１", 
    "すいちゅう２"
  ], 
  "exp": 10240, 
  "friendship": 70, 
  "height": 1.0, 
  "image_url": "http://wiki.gamerp.jp/img/pokemon/369-m.png", 
  "name": "ジーランス", 
  "number": 369, 
  "parameters": {
    "attack": 90, 
    "block": 130, 
    "critical": 45, 
    "defense": 65, 
    "hp": 100, 
    "speed": 55, 
    "total": 485
  }, 
  "species": "ちょうじゅポケモン", 
  "types": [
    "みず", 
    "いわ"
  ], 
  "weight": 23.4
}