{
  "abilities": [
    "ハードロック", 
    "がんじょう", 
    "すいすい"
  ], 
  "egg_groups": [
    "すいちゅう１", 
    "すいちゅう３"
  ], 
  "exp": 7680, 
  "friendship": 70, 
  "height": 0.7, 
  "image_url": "http://wiki.gamerp.jp/img/pokemon/564.png", 
  "name": "プロトーガ", 
  "number": 564, 
  "parameters": {
    "attack": 78, 
    "block": 103, 
    "critical": 53, 
    "defense": 45, 
    "hp": 54, 
    "speed": 22, 
    "total": 355
  }, 
  "species": "こだいがめポケモン", 
  "types": [
    "みず", 
    "いわ"
  ], 
  "weight": 16.5
}